django_tor/__init__.py
django_tor/common.py
django_tor/django_tor.py
django_tor/onion.py
django_tor/onionstart.py
django_tor/settings.py
django_tor/torrc_template
django_tor/torrc_template-windows
django_tor-1.0.1.dist-info/LICENSE
django_tor-1.0.1.dist-info/METADATA
django_tor-1.0.1.dist-info/WHEEL
django_tor-1.0.1.dist-info/top_level.txt
django_tor-1.0.1.dist-info/RECORD
