Metadata-Version: 2.1
Name: django-tor
Version: 1.0.1
Summary: A simple way to run Django apps on tor from your machine.
Home-page: https://github.com/jakbin/django-tor
Author: Jak Bin
License: MIT License
Project-URL: Bug Tracker, https://github.com/jakbin/django-tor/issues
Keywords: django,tor,onion
Platform: UNKNOWN
Classifier: Development Status :: 4 - Beta
Classifier: Programming Language :: Python :: 3.6
Classifier: License :: OSI Approved :: MIT License
Classifier: Operating System :: OS Independent
Requires-Python: >=3
License-File: LICENSE
Requires-Dist: Django
Requires-Dist: stem
